.gitignore
CHANGES.rst
DESCRIPTION.rst
LICENSE
MANIFEST.in
README.md
RELEASE.md
requirements.txt
setup.cfg
setup.py
doc/Makefile
doc/make.bat
doc/source/commandline.rst
doc/source/conf.py
doc/source/examples.rst
doc/source/flow.rst
doc/source/index.rst
doc/source/install.rst
doc/source/modules.rst
doc/source/troubleshooting.rst
doc/source/weka.core.rst
doc/source/weka.flow.rst
doc/source/weka.plot.rst
doc/source/weka.rst
doc/source/_static/logo.jpg
doc/source/_static/logo.pdf
doc/source/_static/logo.png
doc/source/_static/logo.svg
doc/source/_static/screenshot1.png
html/github/redirect.zip
html/pypi/index.html
html/pypi/redirect.zip
html/pypi/sphinx.zip
java/Makefile
java/src/weka/classifiers/EvaluationWrapper.java
java/src/weka/classifiers/KernelHelper.java
java/src/weka/classifiers/timeseries/eval/TSEvalModuleHelper.java
java/src/weka/classifiers/timeseries/eval/TSEvaluationHelper.java
java/src/weka/core/ClassHelper.java
java/src/weka/core/PickleHelper.java
media/channel/channel.xcf
python/__init__.py
python/python_weka_wrapper3.egg-info/PKG-INFO
python/python_weka_wrapper3.egg-info/SOURCES.txt
python/python_weka_wrapper3.egg-info/dependency_links.txt
python/python_weka_wrapper3.egg-info/entry_points.txt
python/python_weka_wrapper3.egg-info/requires.txt
python/python_weka_wrapper3.egg-info/top_level.txt
python/weka/__init__.py
python/weka/associations.py
python/weka/attribute_selection.py
python/weka/classifiers.py
python/weka/clusterers.py
python/weka/datagenerators.py
python/weka/experiments.py
python/weka/filters.py
python/weka/timeseries.py
python/weka/core/__init__.py
python/weka/core/capabilities.py
python/weka/core/classes.py
python/weka/core/converters.py
python/weka/core/database.py
python/weka/core/dataset.py
python/weka/core/distances.py
python/weka/core/jvm.py
python/weka/core/packages.py
python/weka/core/serialization.py
python/weka/core/stemmers.py
python/weka/core/stopwords.py
python/weka/core/systeminfo.py
python/weka/core/tokenizers.py
python/weka/core/typeconv.py
python/weka/core/utils.py
python/weka/core/version.py
python/weka/flow/__init__.py
python/weka/flow/container.py
python/weka/flow/conversion.py
python/weka/flow/sink.py
python/weka/flow/source.py
python/weka/flow/transformer.py
python/weka/lib/arpack_combined.jar
python/weka/lib/core.jar
